xprof/server.py
xprof/profile_plugin_loader.py
xprof/profile_plugin.py
xprof/version.py
xprof/__init__.py
xprof/integration_tests/tf_mnist.py
xprof/integration_tests/tf_profiler_session.py
xprof/integration_tests/tpu/tensorflow/tpu_tf2_keras_test.py
xprof/convert/csv_writer.py
xprof/convert/_pywrap_profiler_plugin.so
xprof/convert/raw_to_tool_data.py
xprof/convert/trace_events_json.py
xprof/static/index.js
xprof/static/trace_viewer_index.js
xprof/static/trace_viewer_index.html
xprof/static/styles.css
xprof/static/index.html
xprof/static/zone.js
xprof/static/bundle.js
xprof/static/materialicons.woff2
xprof/standalone/plugin_asset_util.py
xprof/standalone/plugin_event_multiplexer.py
xprof/standalone/tensorboard_shim.py
xprof/standalone/base_plugin.py
xprof/standalone/data_provider.py
xprof/standalone/context.py
xprof/protobuf/overview_page_pb2.py
xprof/protobuf/event_time_fraction_analyzer_pb2.py
xprof/protobuf/tf_stats_pb2.py
xprof/protobuf/kernel_stats_pb2.py
xprof/protobuf/diagnostics_pb2.py
xprof/protobuf/trace_events_raw_pb2.py
xprof/protobuf/dcn_slack_analysis_pb2.py
xprof/protobuf/memory_profile_pb2.py
xprof/protobuf/pod_viewer_pb2.py
xprof/protobuf/smart_suggestion_pb2.py
xprof/protobuf/power_metrics_pb2.py
xprof/protobuf/trace_events_pb2.py
xprof/protobuf/steps_db_pb2.py
xprof/protobuf/inference_stats_pb2.py
xprof/protobuf/op_profile_pb2.py
xprof/protobuf/trace_filter_config_pb2.py
xprof/protobuf/source_info_pb2.py
xprof/protobuf/source_stats_pb2.py
xprof/protobuf/hardware_types_pb2.py
xprof/protobuf/input_pipeline_pb2.py
xprof/protobuf/tpu_input_pipeline_pb2.py
xprof/protobuf/tf_function_pb2.py
xprof/protobuf/hlo_stats_pb2.py
xprof/protobuf/op_stats_pb2.py
xprof/protobuf/op_metrics_pb2.py
xprof/protobuf/pod_stats_pb2.py
xprof/protobuf/memory_viewer_preprocess_pb2.py
xprof/protobuf/trace_events_old_pb2.py
xprof/protobuf/roofline_model_pb2.py
xprof/protobuf/dcn_collective_info_pb2.py
xprof_nightly-2.22.5a20260130.dist-info/RECORD
xprof_nightly-2.22.5a20260130.dist-info/METADATA
xprof_nightly-2.22.5a20260130.dist-info/top_level.txt
xprof_nightly-2.22.5a20260130.dist-info/WHEEL
xprof_nightly-2.22.5a20260130.dist-info/entry_points.txt
